jgafnea/__init__.py
jgafnea/__main__.py
jgafnea-0.1.0.dist-info/METADATA
jgafnea-0.1.0.dist-info/WHEEL
jgafnea-0.1.0.dist-info/entry_points.txt
jgafnea-0.1.0.dist-info/RECORD
